pycodeutils/__init__.py
pycodeutils/console.py
pycodeutils/core.py
pycodeutils/utils.py
pycodeutils-0.0.1.dist-info/LICENSE
pycodeutils-0.0.1.dist-info/WHEEL
pycodeutils-0.0.1.dist-info/METADATA
pycodeutils-0.0.1.dist-info/RECORD
